genjuice/__init__.py
genjuice/component.py
genjuice/components/__init__.py
genjuice/components/_gen/__init__.py
genjuice/components/_gen/a.py
genjuice/components/_gen/abbr.py
genjuice/components/_gen/address.py
genjuice/components/_gen/area.py
genjuice/components/_gen/article.py
genjuice/components/_gen/aside.py
genjuice/components/_gen/audio.py
genjuice/components/_gen/b.py
genjuice/components/_gen/base.py
genjuice/components/_gen/bdi.py
genjuice/components/_gen/bdo.py
genjuice/components/_gen/blockquote.py
genjuice/components/_gen/body.py
genjuice/components/_gen/br.py
genjuice/components/_gen/button.py
genjuice/components/_gen/canvas.py
genjuice/components/_gen/caption.py
genjuice/components/_gen/cite.py
genjuice/components/_gen/code.py
genjuice/components/_gen/col.py
genjuice/components/_gen/colgroup.py
genjuice/components/_gen/data.py
genjuice/components/_gen/datalist.py
genjuice/components/_gen/dd.py
genjuice/components/_gen/del_.py
genjuice/components/_gen/details.py
genjuice/components/_gen/dfn.py
genjuice/components/_gen/dialog.py
genjuice/components/_gen/div.py
genjuice/components/_gen/dl.py
genjuice/components/_gen/dt.py
genjuice/components/_gen/em.py
genjuice/components/_gen/embed.py
genjuice/components/_gen/fieldset.py
genjuice/components/_gen/figcaption.py
genjuice/components/_gen/figure.py
genjuice/components/_gen/footer.py
genjuice/components/_gen/form.py
genjuice/components/_gen/head.py
genjuice/components/_gen/header.py
genjuice/components/_gen/hgroup.py
genjuice/components/_gen/hr.py
genjuice/components/_gen/html.py
genjuice/components/_gen/i.py
genjuice/components/_gen/iframe.py
genjuice/components/_gen/img.py
genjuice/components/_gen/input.py
genjuice/components/_gen/ins.py
genjuice/components/_gen/kbd.py
genjuice/components/_gen/label.py
genjuice/components/_gen/legend.py
genjuice/components/_gen/li.py
genjuice/components/_gen/link.py
genjuice/components/_gen/main.py
genjuice/components/_gen/map.py
genjuice/components/_gen/mark.py
genjuice-0.1.4.dist-info/LICENSE
genjuice-0.1.4.dist-info/WHEEL
genjuice-0.1.4.dist-info/METADATA
genjuice-0.1.4.dist-info/RECORD
