Metadata-Version: 2.1
Name: genjuice
Version: 0.1.4
Summary: A lightweight, component-based HTML builder
Home-page: https://github.com/docyx/genjuice
License: MIT
Keywords: html,template,css,web
Author: docyx
Author-email: oliverxur@gmail.com
Requires-Python: >=3.8,<4.0
Classifier: Intended Audience :: Developers
Classifier: Intended Audience :: Education
Classifier: License :: OSI Approved :: MIT License
Classifier: Natural Language :: English
Classifier: Operating System :: OS Independent
Classifier: Programming Language :: Python :: 3
Classifier: Programming Language :: Python :: 3.8
Classifier: Programming Language :: Python :: 3.9
Classifier: Topic :: Internet
Classifier: Typing :: Typed
Project-URL: Documentation, https://github.com/docyx/genjuice
Project-URL: Repository, https://github.com/docyx/genjuice
